text_to_speech/__init__.py
text_to_speech/text_to_speech.py
text_to_speech-1.6.1.dist-info/LICENSE
text_to_speech-1.6.1.dist-info/METADATA
text_to_speech-1.6.1.dist-info/WHEEL
text_to_speech-1.6.1.dist-info/top_level.txt
text_to_speech-1.6.1.dist-info/RECORD
