Metadata-Version: 2.1
Name: text-to-speech
Version: 1.6.1
Summary: A versatile and user-friendly Python Text-to-Speech engine
Home-page: https://github.com/dewittethomas/text-to-speech
Author: Thomas Dewitte
Author-email: thomasdewittecontact@gmail.com
License: MIT
Keywords: sound playsound music wave wav mp3 media song play audio
Classifier: Programming Language :: Python :: 3
Classifier: Programming Language :: Python :: 3.8
Classifier: Operating System :: OS Independent
Classifier: License :: OSI Approved :: MIT License
License-File: LICENSE
Requires-Dist: gTTS >=2.3.1
